Metadata-Version: 2.1
Name: distributionsgeneral
Version: 0.2
Summary: Gaussian and Binomial distributionsgeneral
Home-page: UNKNOWN
Author: Amandeep Mander
License: UNKNOWN
Platform: UNKNOWN
